ecdk/__init__.py
ecdk/main.py
ecdk/cli/__init__.py
ecdk/cli/args.py
ecdk/cli/cli.py
ecdk/cli/command.py
ecdk/cli/validation.py
ecdk/command/__init__.py
ecdk/command/analyze.py
ecdk/command/compare.py
ecdk/command/perfcmp.py
ecdk/command/run.py
ecdk/core/__init__.py
ecdk/core/conversion.py
ecdk/core/env.py
ecdk/core/fs.py
ecdk/core/scheduler.py
ecdk/core/series.py
ecdk/core/tools.py
ecdk/core/util.py
ecdk/data/__init__.py
ecdk/data/file_resolver.py
ecdk/data/filter.py
ecdk/data/model.py
ecdk/data/pipeline.py
ecdk/data/plot.py
ecdk/data/processing.py
ecdk/data/stat.py
ecdk/data/tools.py
ecdk/experiment/__init__.py
ecdk/experiment/model.py
ecdk/experiment/runner.py
ecdk/experiment/solver.py
ecdk/problem/__init__.py
ecdk-0.0.1b1.dist-info/METADATA
ecdk-0.0.1b1.dist-info/WHEEL
ecdk-0.0.1b1.dist-info/licenses/LICENSE
ecdk-0.0.1b1.dist-info/RECORD
